painless_timeit/__init__.py
painless_timeit/painless_timeit.py
painless_timeit-0.0.1.dist-info/METADATA
painless_timeit-0.0.1.dist-info/WHEEL
painless_timeit-0.0.1.dist-info/licenses/LICENSE
painless_timeit-0.0.1.dist-info/RECORD
