Metadata-Version: 2.4
Name: painless_timeit
Version: 0.0.1
Summary: A timeit decorator with built-in split functionality for Python
Project-URL: Homepage, https://github.com/6ninjak/painless-timeit
Project-URL: Issues, https://github.com/6ninjak/painless-timeit/issues
Author-email: 6ninjak <6ninjak@gmail.com>
License-Expression: MIT
License-File: LICENSE
Classifier: Operating System :: OS Independent
Classifier: Programming Language :: Python :: 3
Requires-Python: >=3.9
